jan883_eda/__init__.py
jan883_eda/eda.py
jan883_eda/model_selection.py
jan883_eda-0.2.1.dist-info/METADATA
jan883_eda-0.2.1.dist-info/WHEEL
jan883_eda-0.2.1.dist-info/RECORD
